[{"krnr":1,"name":"FRIEDLAND -27\/BARTENSTEIN","nsdap_pct":52.32},{"krnr":2,"name":"BRAUNSBERG","nsdap_pct":29.15},{"krnr":5,"name":"FISCHHAUSEN","nsdap_pct":48.19},{"krnr":6,"name":"GERDAUEN","nsdap_pct":50.24},{"krnr":7,"name":"HEILIGENBEIL","nsdap_pct":51.11},{"krnr":8,"name":"HEILSBERG","nsdap_pct":36.8},{"krnr":9,"name":"KOENIGSBERG (PR) L","nsdap_pct":47.89},{"krnr":11,"name":"LABIAU","nsdap_pct":61.71},{"krnr":12,"name":"MOHRUNGEN","nsdap_pct":56.44},{"krnr":13,"name":"PREUSSISCH EYLAU","nsdap_pct":55.6},{"krnr":14,"name":"PREUSSISCH HOLLAND","nsdap_pct":65.44},{"krnr":15,"name":"RASTENBURG","nsdap_pct":55.33},{"krnr":16,"name":"WEHLAU","nsdap_pct":55.06},{"krnr":17,"name":"ANGERBURG","nsdap_pct":57.39},{"krnr":18,"name":"DARKEHMEN","nsdap_pct":58.05},{"krnr":19,"name":"GOLDAP","nsdap_pct":62.53},{"krnr":20,"name":"GUMBINNEN","nsdap_pct":54.61},{"krnr":22,"name":"INSTERBURG L","nsdap_pct":57.96},{"krnr":24,"name":"NIEDERUNG","nsdap_pct":67.77},{"krnr":25,"name":"OLETZKO (-33\/TREUBURG)","nsdap_pct":74.46},{"krnr":26,"name":"PILLKALLEN","nsdap_pct":61.59},{"krnr":28,"name":"STALLUPOENEN","nsdap_pct":66.3},{"krnr":31,"name":"TILSIT-RAGNIT","nsdap_pct":64.77},{"krnr":32,"name":"ALLENSTEIN L","nsdap_pct":47.41},{"krnr":34,"name":"JOHANNISBURG","nsdap_pct":76.6},{"krnr":35,"name":"LOETZEN","nsdap_pct":72.52},{"krnr":36,"name":"LYCK","nsdap_pct":80.38},{"krnr":37,"name":"NEIDENBURG","nsdap_pct":80.98},{"krnr":38,"name":"ORTELSBURG","nsdap_pct":74.22},{"krnr":39,"name":"OSTERODE I. OSTPR.","nsdap_pct":62.73},{"krnr":40,"name":"ROESSEL","nsdap_pct":38.67},{"krnr":41,"name":"SENSBURG","nsdap_pct":69.02},{"krnr":42,"name":"ELBING L","nsdap_pct":53.46},{"krnr":44,"name":"MARIENBURG (WESTPR.)","nsdap_pct":53.92},{"krnr":45,"name":"MARIENWERDER","nsdap_pct":59.0},{"krnr":46,"name":"ROSENBERG (WESTPR.)","nsdap_pct":61.03},{"krnr":47,"name":"STUHM","nsdap_pct":39.8},{"krnr":73,"name":"BEESKOW-STORKOW","nsdap_pct":50.66},{"krnr":75,"name":"TELTOW","nsdap_pct":41.56},{"krnr":85,"name":"ANGERMUENDE","nsdap_pct":59.12},{"krnr":89,"name":"JUETERBOG-LUCKENWALDE","nsdap_pct":48.12},{"krnr":90,"name":"NIEDERBARNIM","nsdap_pct":43.01},{"krnr":91,"name":"OBERBARNIM","nsdap_pct":49.62},{"krnr":92,"name":"OSTHAVELLAND","nsdap_pct":43.3},{"krnr":93,"name":"OSTPRIGNITZ","nsdap_pct":66.34},{"krnr":95,"name":"PRENZLAU","nsdap_pct":58.57},{"krnr":97,"name":"RUPPIN","nsdap_pct":59.33},{"krnr":99,"name":"TEMPLIN","nsdap_pct":52.13},{"krnr":100,"name":"WESTHAVELLAND","nsdap_pct":49.8},{"krnr":101,"name":"WESTPRIGNITZ","nsdap_pct":60.21},{"krnr":103,"name":"ZAUCH-BELZIG","nsdap_pct":56.86},{"krnr":104,"name":"ARNSWALDE","nsdap_pct":62.05},{"krnr":105,"name":"CALAU","nsdap_pct":44.98},{"krnr":106,"name":"COTTBUS L","nsdap_pct":61.08},{"krnr":108,"name":"CROSSEN (ODER)","nsdap_pct":64.13},{"krnr":111,"name":"FRIEDEBERG (NEUMARK)","nsdap_pct":64.35},{"krnr":112,"name":"GUBEN L","nsdap_pct":63.35},{"krnr":114,"name":"KOENIGSBERG (NEUMARK)","nsdap_pct":55.76},{"krnr":115,"name":"LANDSBERG (WARTHE) L","nsdap_pct":66.17},{"krnr":117,"name":"LEBUS","nsdap_pct":51.43},{"krnr":118,"name":"LUEBBEN","nsdap_pct":69.34},{"krnr":119,"name":"LUCKAU","nsdap_pct":53.7},{"krnr":120,"name":"OSTSTERNBERG","nsdap_pct":65.34},{"krnr":121,"name":"SOLDIN","nsdap_pct":64.62},{"krnr":122,"name":"SORAU","nsdap_pct":53.73},{"krnr":123,"name":"SPREMBERG (LAUSITZ)","nsdap_pct":41.0},{"krnr":124,"name":"WESTSTERNBERG","nsdap_pct":59.26},{"krnr":125,"name":"ZUELLICHAU-SCHWIEBUS","nsdap_pct":63.85},{"krnr":126,"name":"BOMST","nsdap_pct":55.62},{"krnr":127,"name":"DEUTSCH KRONE","nsdap_pct":48.44},{"krnr":128,"name":"FLATOW","nsdap_pct":64.72},{"krnr":129,"name":"FRAUSTADT","nsdap_pct":53.85},{"krnr":130,"name":"MESERITZ","nsdap_pct":48.65},{"krnr":131,"name":"NETZEKREIS","nsdap_pct":62.28},{"krnr":132,"name":"SCHLOCHAU","nsdap_pct":50.45},{"krnr":134,"name":"SCHWERIN (WARTHE)","nsdap_pct":40.77},{"krnr":135,"name":"ANKLAM","nsdap_pct":51.7},{"krnr":136,"name":"CAMMIN","nsdap_pct":63.31},{"krnr":137,"name":"DEMMIN","nsdap_pct":57.5},{"krnr":138,"name":"FRANZBURG-BARTH","nsdap_pct":50.55},{"krnr":139,"name":"GREIFENBERG","nsdap_pct":63.58},{"krnr":140,"name":"GREIFENHAGEN","nsdap_pct":61.74},{"krnr":141,"name":"GREIFSWALD L","nsdap_pct":51.49},{"krnr":143,"name":"GRIMMEN","nsdap_pct":52.5},{"krnr":144,"name":"NAUGARD","nsdap_pct":62.59},{"krnr":145,"name":"PYRITZ","nsdap_pct":64.43},{"krnr":146,"name":"RANDOW","nsdap_pct":49.94},{"krnr":147,"name":"REGENWALDE","nsdap_pct":62.72},{"krnr":148,"name":"RUEGEN","nsdap_pct":53.57},{"krnr":149,"name":"SAATZIG","nsdap_pct":61.58},{"krnr":153,"name":"UECKERMUENDE","nsdap_pct":51.83},{"krnr":154,"name":"USEDOM-WOLLIN","nsdap_pct":57.25},{"krnr":155,"name":"BELGARD","nsdap_pct":62.28},{"krnr":157,"name":"BUETOW","nsdap_pct":57.81},{"krnr":158,"name":"DRAMBURG","nsdap_pct":67.19},{"krnr":160,"name":"KOLBERG-KOERLIN","nsdap_pct":64.6},{"krnr":161,"name":"KOESLIN L","nsdap_pct":64.54},{"krnr":164,"name":"LAUENBURG (POMMERN)","nsdap_pct":63.08},{"krnr":165,"name":"NEUSTETTIN","nsdap_pct":64.76},{"krnr":166,"name":"RUMMELSBURG","nsdap_pct":63.01},{"krnr":168,"name":"SCHLAWE","nsdap_pct":58.15},{"krnr":169,"name":"STOLP L","nsdap_pct":55.94},{"krnr":178,"name":"BRESLAU L","nsdap_pct":47.85},{"krnr":180,"name":"BRIEG L","nsdap_pct":59.62},{"krnr":182,"name":"FRANKENSTEIN","nsdap_pct":45.19},{"krnr":183,"name":"GLATZ","nsdap_pct":38.6},{"krnr":184,"name":"GROSS WARTENBERG","nsdap_pct":52.26},{"krnr":185,"name":"GUHRAU","nsdap_pct":68.21},{"krnr":186,"name":"HABELSCHWERDT","nsdap_pct":54.84},{"krnr":187,"name":"MILITSCH","nsdap_pct":62.93},{"krnr":189,"name":"NAMSLAU (=NAMSLAU-REST)","nsdap_pct":50.87},{"krnr":190,"name":"NEUMARKT (SCHLESIEN)","nsdap_pct":53.38},{"krnr":193,"name":"OELS","nsdap_pct":63.04},{"krnr":195,"name":"REICHENBACH","nsdap_pct":46.87},{"krnr":196,"name":"SCHWEIDNITZ L","nsdap_pct":42.2},{"krnr":199,"name":"STREHLEN","nsdap_pct":54.85},{"krnr":201,"name":"TREBNITZ","nsdap_pct":61.18},{"krnr":202,"name":"WALDENBURG (SCHLESIEN) L","nsdap_pct":43.98},{"krnr":205,"name":"WOHLAU","nsdap_pct":60.77},{"krnr":207,"name":"BUNZLAU","nsdap_pct":51.32},{"krnr":209,"name":"GLOGAU L","nsdap_pct":60.38},{"krnr":212,"name":"GOLDBERG","nsdap_pct":61.55},{"krnr":214,"name":"GOERLITZ L","nsdap_pct":54.63},{"krnr":216,"name":"GRUENBERG L","nsdap_pct":56.81},{"krnr":219,"name":"HIRSCHBERG L","nsdap_pct":53.08},{"krnr":222,"name":"HOYERSWERDA","nsdap_pct":48.47},{"krnr":224,"name":"LANDESHUT","nsdap_pct":54.25},{"krnr":225,"name":"LAUBAN","nsdap_pct":58.91},{"krnr":226,"name":"LIEGNITZ L","nsdap_pct":59.11},{"krnr":228,"name":"LOEWENBERG","nsdap_pct":60.48},{"krnr":229,"name":"LUEBEN","nsdap_pct":66.57},{"krnr":230,"name":"ROTHENBURG (OBERLAUSITZ)","nsdap_pct":45.5},{"krnr":233,"name":"SPROTTAU","nsdap_pct":53.61},{"krnr":236,"name":"BEUTHEN-TARNOWITZ (1.1.27-)","nsdap_pct":39.08},{"krnr":238,"name":"COSEL","nsdap_pct":44.64},{"krnr":239,"name":"FALKENBERG","nsdap_pct":41.81},{"krnr":241,"name":"GROSS STREHLITZ","nsdap_pct":40.73},{"krnr":242,"name":"GROTTKAU","nsdap_pct":51.14},{"krnr":243,"name":"LUBLINITZ (-31.12.26)\/GUTTENTAG","nsdap_pct":51.44},{"krnr":246,"name":"KREUZBURG","nsdap_pct":55.18},{"krnr":247,"name":"LEOBSCHUETZ","nsdap_pct":43.37},{"krnr":248,"name":"NEISSE L","nsdap_pct":38.37},{"krnr":250,"name":"NEUSTADT (O.S)","nsdap_pct":40.4},{"krnr":251,"name":"OPPELN L","nsdap_pct":39.99},{"krnr":253,"name":"RATIBOR L","nsdap_pct":41.48},{"krnr":255,"name":"ROSENBERG (O.S)","nsdap_pct":37.13},{"krnr":257,"name":"TOST-GLEIWITZ","nsdap_pct":42.14},{"krnr":260,"name":"CALBE","nsdap_pct":40.61},{"krnr":261,"name":"GARDELEGEN","nsdap_pct":60.32},{"krnr":262,"name":"GRAFSCHAFT WERNIGERODE (","nsdap_pct":55.9},{"krnr":265,"name":"JERICHOW I","nsdap_pct":56.53},{"krnr":266,"name":"JERICHOW II","nsdap_pct":50.79},{"krnr":268,"name":"NEUHALDENSLEBEN","nsdap_pct":46.95},{"krnr":269,"name":"OSCHERSLEBEN","nsdap_pct":47.22},{"krnr":270,"name":"OSTERBURG","nsdap_pct":60.11},{"krnr":271,"name":"QUEDLINBURG L","nsdap_pct":48.05},{"krnr":273,"name":"SALZWEDEL","nsdap_pct":63.89},{"krnr":274,"name":"STENDAL L","nsdap_pct":51.08},{"krnr":276,"name":"WANZLEBEN","nsdap_pct":41.06},{"krnr":277,"name":"WOLMIRSTEDT","nsdap_pct":43.07},{"krnr":278,"name":"BALLENSTEDT","nsdap_pct":46.93},{"krnr":279,"name":"BERNBURG","nsdap_pct":41.82},{"krnr":283,"name":"DESSAU-KOETHEN","nsdap_pct":46.7},{"krnr":287,"name":"ZERBST","nsdap_pct":50.44},{"krnr":288,"name":"BITTERFELD","nsdap_pct":37.43},{"krnr":289,"name":"DELITZSCH","nsdap_pct":46.63},{"krnr":290,"name":"ECKARTSBERGA","nsdap_pct":66.82},{"krnr":293,"name":"LIEBENWERDA","nsdap_pct":55.56},{"krnr":294,"name":"MANSFELDER GEBIRGSKREIS","nsdap_pct":46.41},{"krnr":295,"name":"MANSFELDER SEEKREIS","nsdap_pct":42.62},{"krnr":297,"name":"MERSEBURG L","nsdap_pct":41.32},{"krnr":301,"name":"QUERFURT","nsdap_pct":51.99},{"krnr":302,"name":"SAALKREIS","nsdap_pct":36.64},{"krnr":303,"name":"SANGERHAUSEN","nsdap_pct":51.12},{"krnr":304,"name":"SCHWEINITZ","nsdap_pct":69.88},{"krnr":305,"name":"TORGAU","nsdap_pct":58.97},{"krnr":306,"name":"WEISSENFELS L","nsdap_pct":43.47},{"krnr":309,"name":"WITTENBERG L","nsdap_pct":51.24},{"krnr":311,"name":"ZEITZ L","nsdap_pct":38.88},{"krnr":313,"name":"ALTENBURG L","nsdap_pct":37.59},{"krnr":316,"name":"ARNSTADT L","nsdap_pct":47.17},{"krnr":318,"name":"KREISABTEILUNG CAMBURG","nsdap_pct":49.49},{"krnr":319,"name":"EISENACH L","nsdap_pct":41.25},{"krnr":323,"name":"GERA L","nsdap_pct":45.77},{"krnr":325,"name":"GOTHA L","nsdap_pct":54.01},{"krnr":328,"name":"GREIZ L","nsdap_pct":52.23},{"krnr":330,"name":"HILDBURGHAUSEN","nsdap_pct":63.09},{"krnr":335,"name":"MEININGEN","nsdap_pct":56.25},{"krnr":339,"name":"RUDOLSTADT","nsdap_pct":39.3},{"krnr":340,"name":"SAALFELD","nsdap_pct":45.36},{"krnr":341,"name":"SCHLEIZ","nsdap_pct":55.63},{"krnr":342,"name":"SONDERSHAUSEN","nsdap_pct":52.34},{"krnr":344,"name":"SONNEBERG","nsdap_pct":54.02},{"krnr":345,"name":"RODA (-24,STADTRODA)","nsdap_pct":40.71},{"krnr":348,"name":"WEIMAR L","nsdap_pct":57.78},{"krnr":358,"name":"GRAFSCHAFT HOHENSTEIN","nsdap_pct":47.93},{"krnr":359,"name":"HEILIGENSTADT","nsdap_pct":21.9},{"krnr":360,"name":"LANGENSALZA","nsdap_pct":59.67},{"krnr":361,"name":"MUEHLHAUSEN L","nsdap_pct":47.33},{"krnr":365,"name":"SCHLEUSINGEN","nsdap_pct":47.6},{"krnr":366,"name":"WEISSENSEE","nsdap_pct":58.82},{"krnr":367,"name":"WORBIS","nsdap_pct":28.96},{"krnr":368,"name":"ZIEGENRUECK","nsdap_pct":50.63},{"krnr":369,"name":"HERRSCHAFT SCHMALKALDEN  (-24 SCHMALKALDEN)","nsdap_pct":54.62},{"krnr":372,"name":"ECKERNFOERDE","nsdap_pct":56.36},{"krnr":373,"name":"EIDERSTEDT","nsdap_pct":63.23},{"krnr":374,"name":"FLENSBURG L","nsdap_pct":71.59},{"krnr":376,"name":"HERZOGTUM LAUENBURG","nsdap_pct":52.02},{"krnr":377,"name":"HUSUM","nsdap_pct":68.5},{"krnr":381,"name":"NORDERDITHMARSCHEN","nsdap_pct":68.58},{"krnr":382,"name":"OLDENBURG","nsdap_pct":50.14},{"krnr":383,"name":"PINNEBERG","nsdap_pct":53.65},{"krnr":384,"name":"PLOEN","nsdap_pct":51.95},{"krnr":385,"name":"RENDSBURG","nsdap_pct":66.29},{"krnr":386,"name":"SCHLESWIG","nsdap_pct":69.43},{"krnr":387,"name":"SEGEBERG","nsdap_pct":66.64},{"krnr":388,"name":"STEINBURG","nsdap_pct":55.1},{"krnr":389,"name":"STORMARN","nsdap_pct":45.77},{"krnr":390,"name":"SUED TONDERN","nsdap_pct":73.48},{"krnr":391,"name":"SUEDERDITHMARSCHEN","nsdap_pct":63.67},{"krnr":394,"name":"LANDESTEIL LUEBECK","nsdap_pct":48.76},{"krnr":396,"name":"ASCHENDORF-HUEMMLING","nsdap_pct":20.12},{"krnr":397,"name":"BERSENBRUECK","nsdap_pct":36.82},{"krnr":398,"name":"GRAFSCHAFT BENTHEIM","nsdap_pct":53.43},{"krnr":401,"name":"LINGEN","nsdap_pct":22.28},{"krnr":402,"name":"MELLE","nsdap_pct":41.55},{"krnr":403,"name":"MEPPEN","nsdap_pct":22.09},{"krnr":404,"name":"OSNABRUECK L","nsdap_pct":29.81},{"krnr":406,"name":"WITTLAGE","nsdap_pct":56.86},{"krnr":407,"name":"AURICH","nsdap_pct":67.79},{"krnr":410,"name":"LEER","nsdap_pct":56.63},{"krnr":411,"name":"NORDEN","nsdap_pct":53.15},{"krnr":414,"name":"WITTMUND","nsdap_pct":70.96},{"krnr":416,"name":"BRAKE (-14.5.33)","nsdap_pct":50.68},{"krnr":417,"name":"BUTJADINGEN (-14.5.33)","nsdap_pct":47.3},{"krnr":418,"name":"CLOPPENBURG","nsdap_pct":28.19},{"krnr":420,"name":"DELMENHORST L (-14.5.33)","nsdap_pct":57.29},{"krnr":422,"name":"ELSFLETH (-14.5.33)","nsdap_pct":60.68},{"krnr":424,"name":"FRIESOYTHE (-14.5.33)","nsdap_pct":32.92},{"krnr":425,"name":"JEVER L (-14.5.33)","nsdap_pct":62.86},{"krnr":427,"name":"OLDENBURG (OLDENBURG) L","nsdap_pct":65.63},{"krnr":431,"name":"VAREL L (-14.5.33)","nsdap_pct":71.29},{"krnr":433,"name":"VECHTA","nsdap_pct":13.29},{"krnr":435,"name":"WESTERSTEDE (-14.5.33)","nsdap_pct":74.1},{"krnr":436,"name":"WILDESHAUSEN (-14.5.33)","nsdap_pct":59.53},{"krnr":437,"name":"BREMEN L","nsdap_pct":33.54},{"krnr":442,"name":"BURGDORF","nsdap_pct":56.64},{"krnr":443,"name":"CELLE L","nsdap_pct":60.21},{"krnr":445,"name":"DANNENBERG","nsdap_pct":69.54},{"krnr":446,"name":"FALLINGBOSTEL","nsdap_pct":66.05},{"krnr":447,"name":"GIFHORN","nsdap_pct":74.21},{"krnr":451,"name":"HARBURG","nsdap_pct":62.06},{"krnr":454,"name":"LUENEBURG L","nsdap_pct":58.84},{"krnr":456,"name":"SOLTAU","nsdap_pct":68.33},{"krnr":457,"name":"UELZEN","nsdap_pct":62.49},{"krnr":461,"name":"BREMERVOERDE","nsdap_pct":67.3},{"krnr":465,"name":"HADELN L","nsdap_pct":55.41},{"krnr":470,"name":"OSTERHOLZ","nsdap_pct":40.14},{"krnr":471,"name":"ROTENBURG (HANNOVER)","nsdap_pct":65.03},{"krnr":472,"name":"STADE","nsdap_pct":59.54},{"krnr":473,"name":"VERDEN","nsdap_pct":49.89},{"krnr":474,"name":"WESERMUENDE  L","nsdap_pct":61.93},{"krnr":477,"name":"GRAFSCHAFT DIEPHOLZ (KREIS DIEPHOLZ)","nsdap_pct":72.92},{"krnr":480,"name":"HAMELN-PYRMONT","nsdap_pct":54.35},{"krnr":481,"name":"HANNOVER L","nsdap_pct":40.69},{"krnr":483,"name":"GRAFSCHAFT HOYA (KREIS HOYA)","nsdap_pct":60.13},{"krnr":485,"name":"NEUSTADT (A. RUEBENBERGE)","nsdap_pct":63.46},{"krnr":486,"name":"NIENBURG","nsdap_pct":64.22},{"krnr":487,"name":"SPRINGE","nsdap_pct":50.27},{"krnr":491,"name":"ALFELD","nsdap_pct":46.3},{"krnr":492,"name":"DUDERSTADT","nsdap_pct":25.13},{"krnr":493,"name":"EINBECK","nsdap_pct":59.76},{"krnr":495,"name":"GOSLAR L","nsdap_pct":49.41},{"krnr":497,"name":"GOETTINGEN L","nsdap_pct":57.26},{"krnr":500,"name":"HILDESHEIM L","nsdap_pct":28.96},{"krnr":503,"name":"MARIENBURG I. HANN.","nsdap_pct":41.96},{"krnr":504,"name":"MUENDEN","nsdap_pct":51.68},{"krnr":505,"name":"NORTHEIM","nsdap_pct":60.54},{"krnr":506,"name":"OSTERODE (HARZ)","nsdap_pct":50.56},{"krnr":507,"name":"PEINE","nsdap_pct":49.16},{"krnr":509,"name":"ZELLERFELD","nsdap_pct":55.93},{"krnr":510,"name":"BLANKENBURG","nsdap_pct":46.66},{"krnr":511,"name":"BRAUNSCHWEIG L","nsdap_pct":56.06},{"krnr":514,"name":"GANDERSHEIM","nsdap_pct":50.16},{"krnr":515,"name":"HELMSTEDT","nsdap_pct":51.0},{"krnr":516,"name":"HOLZMINDEN","nsdap_pct":48.81},{"krnr":517,"name":"WOLFENBUETTEL","nsdap_pct":54.9},{"krnr":518,"name":"AHAUS","nsdap_pct":21.49},{"krnr":519,"name":"BECKUM","nsdap_pct":25.39},{"krnr":521,"name":"BORKEN","nsdap_pct":23.39},{"krnr":525,"name":"COESFELD","nsdap_pct":21.48},{"krnr":529,"name":"LUEDINGHAUSEN","nsdap_pct":24.98},{"krnr":530,"name":"MUENSTER L","nsdap_pct":26.86},{"krnr":533,"name":"RECKLINGHAUSEN L","nsdap_pct":27.12},{"krnr":535,"name":"STEINFURT","nsdap_pct":22.48},{"krnr":536,"name":"TECKLENBURG","nsdap_pct":42.75},{"krnr":537,"name":"WARENDORF","nsdap_pct":29.63},{"krnr":538,"name":"BIELEFELD L","nsdap_pct":40.34},{"krnr":540,"name":"BUEREN","nsdap_pct":19.73},{"krnr":541,"name":"HALLE (WESTFALEN)","nsdap_pct":62.41},{"krnr":542,"name":"HERFORD L","nsdap_pct":49.63},{"krnr":544,"name":"HOEXTER","nsdap_pct":25.05},{"krnr":545,"name":"LUEBBECKE","nsdap_pct":71.41},{"krnr":546,"name":"MINDEN","nsdap_pct":48.37},{"krnr":547,"name":"PADERBORN","nsdap_pct":23.73},{"krnr":548,"name":"WARBURG","nsdap_pct":21.78},{"krnr":549,"name":"WIEDENBRUECK","nsdap_pct":33.25},{"krnr":551,"name":"GRAFSCHAFT SCHAUMBURG","nsdap_pct":53.61},{"krnr":553,"name":"BUECKEBURG L","nsdap_pct":37.16},{"krnr":555,"name":"STADTHAGEN L","nsdap_pct":50.73},{"krnr":568,"name":"DETMOLD L  (1.4.32-)","nsdap_pct":45.72},{"krnr":574,"name":"LEMGO L  (1.4.32-)","nsdap_pct":49.47},{"krnr":589,"name":"ALTENA","nsdap_pct":46.58},{"krnr":590,"name":"ARNSBERG","nsdap_pct":20.94},{"krnr":593,"name":"BRILON","nsdap_pct":22.61},{"krnr":597,"name":"ENNEPE-RUHRKREIS","nsdap_pct":38.68},{"krnr":608,"name":"ISERLOHN L","nsdap_pct":35.72},{"krnr":610,"name":"LIPPSTADT","nsdap_pct":24.35},{"krnr":613,"name":"MESCHEDE","nsdap_pct":23.14},{"krnr":614,"name":"OLPE","nsdap_pct":14.34},{"krnr":617,"name":"SIEGEN L","nsdap_pct":56.27},{"krnr":619,"name":"SOEST","nsdap_pct":41.49},{"krnr":620,"name":"UNNA (-16.10.30 HAMM L)","nsdap_pct":38.5},{"krnr":624,"name":"WITTGENSTEIN","nsdap_pct":71.6},{"krnr":625,"name":"ESCHWEGE","nsdap_pct":55.5},{"krnr":626,"name":"FRANKENBERG","nsdap_pct":78.17},{"krnr":628,"name":"FRITZLAR-HOMBERG","nsdap_pct":61.68},{"krnr":630,"name":"FULDA L","nsdap_pct":28.36},{"krnr":632,"name":"GELNHAUSEN","nsdap_pct":48.46},{"krnr":634,"name":"HANAU L","nsdap_pct":39.31},{"krnr":636,"name":"HERSFELD","nsdap_pct":59.11},{"krnr":637,"name":"HOFGEISMAR","nsdap_pct":57.89},{"krnr":639,"name":"HUENFELD","nsdap_pct":37.76},{"krnr":640,"name":"KASSEL L","nsdap_pct":42.82},{"krnr":643,"name":"KREIS DER EDER","nsdap_pct":71.32},{"krnr":644,"name":"KREIS DER TWISTE","nsdap_pct":70.97},{"krnr":645,"name":"KREIS DES EISENBERGES","nsdap_pct":70.39},{"krnr":647,"name":"MARBURG L","nsdap_pct":62.95},{"krnr":649,"name":"MELSUNGEN","nsdap_pct":61.71},{"krnr":650,"name":"ROTENBURG (HESSEN-NASSAU)","nsdap_pct":68.98},{"krnr":651,"name":"SCHLUECHTERN","nsdap_pct":56.02},{"krnr":652,"name":"WITZENHAUSEN","nsdap_pct":55.98},{"krnr":653,"name":"WOLFHAGEN","nsdap_pct":58.13},{"krnr":654,"name":"ZIEGENHAIN","nsdap_pct":77.96},{"krnr":656,"name":"DILLENBURG","nsdap_pct":72.72},{"krnr":659,"name":"LIMBURG","nsdap_pct":31.84},{"krnr":662,"name":"MAIN-TAUNUSKREIS (1.4.28","nsdap_pct":40.5},{"krnr":663,"name":"OBERLAHNKREIS","nsdap_pct":52.79},{"krnr":664,"name":"OBERTAUNUSKREIS","nsdap_pct":45.7},{"krnr":665,"name":"OBERWESTERWALDKREIS","nsdap_pct":48.41},{"krnr":666,"name":"RHEINGAUKREIS","nsdap_pct":30.94},{"krnr":667,"name":"SANKT GOARSHAUSEN","nsdap_pct":53.82},{"krnr":668,"name":"UNTERLAHNKREIS","nsdap_pct":56.07},{"krnr":669,"name":"UNTERTAUNUSKREIS","nsdap_pct":63.47},{"krnr":670,"name":"UNTERWESTERWALDKREIS","nsdap_pct":30.14},{"krnr":673,"name":"WETZLAR","nsdap_pct":53.97},{"krnr":680,"name":"BERGHEIM","nsdap_pct":20.48},{"krnr":681,"name":"BONN L","nsdap_pct":31.58},{"krnr":683,"name":"EUSKIRCHEN","nsdap_pct":32.81},{"krnr":685,"name":"KOELN L","nsdap_pct":23.53},{"krnr":688,"name":"OBERBERGISCHER KREIS","nsdap_pct":47.49},{"krnr":690,"name":"RHEINISCH-BERGISCHER KREIS","nsdap_pct":24.98},{"krnr":691,"name":"SIEGKREIS","nsdap_pct":29.63},{"krnr":694,"name":"AACHEN L","nsdap_pct":23.03},{"krnr":696,"name":"DUEREN","nsdap_pct":21.74},{"krnr":697,"name":"ERKELENZ","nsdap_pct":34.66},{"krnr":698,"name":"GEILENKIRCHEN (-9.8.33)\/GEILENK.-HEINSBERG","nsdap_pct":30.2},{"krnr":700,"name":"JUELICH","nsdap_pct":29.94},{"krnr":701,"name":"MONSCHAU","nsdap_pct":28.18},{"krnr":702,"name":"SCHLEIDEN","nsdap_pct":32.23},{"krnr":704,"name":"AHRWEILER","nsdap_pct":24.07},{"krnr":705,"name":"ALTENKIRCHEN","nsdap_pct":37.17},{"krnr":706,"name":"COCHEM","nsdap_pct":41.48},{"krnr":707,"name":"KOBLENZ L","nsdap_pct":30.62},{"krnr":709,"name":"KREUZNACH","nsdap_pct":42.52},{"krnr":710,"name":"MAYEN","nsdap_pct":30.56},{"krnr":712,"name":"NEUWIED","nsdap_pct":33.81},{"krnr":713,"name":"SANKT GOAR","nsdap_pct":37.17},{"krnr":714,"name":"SIMMERN","nsdap_pct":52.92},{"krnr":715,"name":"ZELL","nsdap_pct":53.99},{"krnr":716,"name":"BERNKASTEL","nsdap_pct":50.3},{"krnr":717,"name":"BITBURG","nsdap_pct":36.19},{"krnr":718,"name":"DAUN","nsdap_pct":32.47},{"krnr":719,"name":"MERZIG-WADERN (REST) (1920  MERZIG)","nsdap_pct":19.52},{"krnr":720,"name":"PRUEM","nsdap_pct":30.74},{"krnr":721,"name":"SAARBURG","nsdap_pct":41.76},{"krnr":723,"name":"ST WENDEL-BAUMHOLDER (1930- \"(REST)\")","nsdap_pct":52.41},{"krnr":724,"name":"TRIER L","nsdap_pct":38.83},{"krnr":726,"name":"WITTLICH","nsdap_pct":45.86},{"krnr":727,"name":"LANDESTEIL BIRKENFELD","nsdap_pct":55.11},{"krnr":731,"name":"DUESSELDORF-METTMANN","nsdap_pct":36.49},{"krnr":738,"name":"RHEIN-WUPPER-KREIS (=SOLINGEN-LENNEP)","nsdap_pct":39.01},{"krnr":742,"name":"CLEVE","nsdap_pct":26.7},{"krnr":743,"name":"DINSLAKEN","nsdap_pct":41.38},{"krnr":746,"name":"GELDERN","nsdap_pct":33.59},{"krnr":750,"name":"GREVENBROICH-NEUSS","nsdap_pct":36.24},{"krnr":753,"name":"KEMPEN-KREFELD","nsdap_pct":30.11},{"krnr":757,"name":"MOERS","nsdap_pct":40.0},{"krnr":763,"name":"REES","nsdap_pct":36.38},{"krnr":767,"name":"AIBLING","nsdap_pct":47.59},{"krnr":768,"name":"AICHACH","nsdap_pct":38.09},{"krnr":769,"name":"ALTOETTING","nsdap_pct":25.65},{"krnr":771,"name":"BERCHTESGADEN","nsdap_pct":46.99},{"krnr":772,"name":"DACHAU","nsdap_pct":29.47},{"krnr":773,"name":"EBERSBERG","nsdap_pct":47.44},{"krnr":774,"name":"ERDING","nsdap_pct":37.84},{"krnr":775,"name":"FREISING L","nsdap_pct":40.74},{"krnr":777,"name":"FRIEDBERG","nsdap_pct":33.73},{"krnr":778,"name":"FUERSTENFELDBRUCK","nsdap_pct":35.08},{"krnr":779,"name":"GARMISCH","nsdap_pct":46.21},{"krnr":780,"name":"INGOLSTADT L","nsdap_pct":37.49},{"krnr":782,"name":"LANDSBERG L","nsdap_pct":48.98},{"krnr":784,"name":"LAUFEN","nsdap_pct":29.67},{"krnr":785,"name":"MIESBACH","nsdap_pct":46.6},{"krnr":786,"name":"MUEHLDORF","nsdap_pct":31.57},{"krnr":787,"name":"MUENCHEN L","nsdap_pct":41.01},{"krnr":789,"name":"PFAFFENHOFEN A.D.ILM","nsdap_pct":50.15},{"krnr":790,"name":"ROSENHEIM  L","nsdap_pct":45.86},{"krnr":792,"name":"SCHONGAU","nsdap_pct":39.42},{"krnr":793,"name":"SCHROBENHAUSEN","nsdap_pct":37.29},{"krnr":794,"name":"STARNBERG","nsdap_pct":43.66},{"krnr":795,"name":"TOELZ","nsdap_pct":47.92},{"krnr":796,"name":"TRAUNSTEIN L","nsdap_pct":34.98},{"krnr":798,"name":"WASSERBURG (INN)","nsdap_pct":38.45},{"krnr":799,"name":"WEILHEIM","nsdap_pct":36.24},{"krnr":800,"name":"WOLFRATSHAUSEN","nsdap_pct":50.14},{"krnr":801,"name":"AUGSBURG L","nsdap_pct":38.08},{"krnr":803,"name":"DILLINGEN (DONAU) L","nsdap_pct":52.62},{"krnr":805,"name":"DONAUWOERTH L","nsdap_pct":52.74},{"krnr":807,"name":"FUESSEN","nsdap_pct":54.31},{"krnr":808,"name":"GUENZBURG L","nsdap_pct":52.01},{"krnr":810,"name":"ILLERTISSEN","nsdap_pct":40.89},{"krnr":811,"name":"KAUFBEUREN L","nsdap_pct":53.29},{"krnr":813,"name":"KEMPTEN L","nsdap_pct":50.19},{"krnr":815,"name":"KRUMBACH","nsdap_pct":45.68},{"krnr":816,"name":"LINDAU (BODENSEE) L","nsdap_pct":51.87},{"krnr":818,"name":"MARKT OBERDORF","nsdap_pct":56.55},{"krnr":819,"name":"MEMMINGEN L","nsdap_pct":50.53},{"krnr":821,"name":"MINDELHEIM","nsdap_pct":42.42},{"krnr":822,"name":"NEU-ULM L","nsdap_pct":52.79},{"krnr":824,"name":"NEUBURG (DONAU) L","nsdap_pct":56.1},{"krnr":826,"name":"NOERDLINGEN L","nsdap_pct":60.41},{"krnr":828,"name":"SCHWABMUENCHEN","nsdap_pct":46.6},{"krnr":829,"name":"SONTHOFEN","nsdap_pct":54.22},{"krnr":830,"name":"WERTINGEN","nsdap_pct":59.69},{"krnr":832,"name":"BOGEN","nsdap_pct":40.98},{"krnr":833,"name":"DEGGENDORF L","nsdap_pct":38.1},{"krnr":835,"name":"DINGOLFING","nsdap_pct":45.36},{"krnr":836,"name":"EGGENFELDEN","nsdap_pct":41.73},{"krnr":837,"name":"GRAFENAU","nsdap_pct":41.97},{"krnr":838,"name":"GRIESBACH","nsdap_pct":62.24},{"krnr":839,"name":"KELHEIM","nsdap_pct":40.82},{"krnr":840,"name":"KOETZTING","nsdap_pct":45.33},{"krnr":841,"name":"LANDAU A.D.ISAR","nsdap_pct":26.54},{"krnr":842,"name":"LANDSHUT L","nsdap_pct":39.57},{"krnr":844,"name":"MAINBURG","nsdap_pct":46.57},{"krnr":845,"name":"MALLERSDORF","nsdap_pct":41.65},{"krnr":846,"name":"PASSAU L","nsdap_pct":44.5},{"krnr":848,"name":"PFARRKIRCHEN","nsdap_pct":55.38},{"krnr":849,"name":"REGEN","nsdap_pct":43.84},{"krnr":850,"name":"ROTTENBURG","nsdap_pct":51.41},{"krnr":851,"name":"STRAUBING L","nsdap_pct":44.3},{"krnr":853,"name":"VIECHTACH","nsdap_pct":48.57},{"krnr":854,"name":"VILSBIBURG","nsdap_pct":32.29},{"krnr":855,"name":"VILSHOFEN","nsdap_pct":53.61},{"krnr":856,"name":"WEGSCHEID","nsdap_pct":49.34},{"krnr":857,"name":"WOLFSTEIN","nsdap_pct":52.88},{"krnr":858,"name":"AMBERG L","nsdap_pct":26.25},{"krnr":860,"name":"BEILNGRIES","nsdap_pct":38.24},{"krnr":861,"name":"BURGLENGENFELD","nsdap_pct":23.06},{"krnr":862,"name":"CHAM","nsdap_pct":33.03},{"krnr":863,"name":"ESCHENBACH (OBERPFALZ)","nsdap_pct":27.42},{"krnr":864,"name":"KEMNATH","nsdap_pct":36.53},{"krnr":865,"name":"NABBURG","nsdap_pct":34.35},{"krnr":866,"name":"NEUMARKT (OBERPFALZ) L","nsdap_pct":39.84},{"krnr":868,"name":"NEUNBURG (V.WALD)","nsdap_pct":33.84},{"krnr":869,"name":"NEUSTADT (WALDNAAB)","nsdap_pct":30.52},{"krnr":870,"name":"OBERVIECHTACH","nsdap_pct":45.28},{"krnr":871,"name":"PARSBERG","nsdap_pct":43.97},{"krnr":872,"name":"REGENSBURG L","nsdap_pct":38.48},{"krnr":874,"name":"RIEDENBURG","nsdap_pct":43.39},{"krnr":875,"name":"RODING","nsdap_pct":30.05},{"krnr":878,"name":"SULZBACH","nsdap_pct":53.13},{"krnr":879,"name":"TIRSCHENREUTH","nsdap_pct":30.1},{"krnr":880,"name":"VOHENSTRAUSS","nsdap_pct":34.52},{"krnr":881,"name":"WALDMUENCHEN","nsdap_pct":38.69},{"krnr":890,"name":"BAMBERG L","nsdap_pct":31.69},{"krnr":892,"name":"BAYREUTH L","nsdap_pct":59.35},{"krnr":895,"name":"COBURG L","nsdap_pct":58.89},{"krnr":897,"name":"EBERMANNSTADT","nsdap_pct":50.51},{"krnr":898,"name":"FORCHHEIM L","nsdap_pct":39.27},{"krnr":900,"name":"HOECHSTADT (AISCH)","nsdap_pct":41.96},{"krnr":901,"name":"HOF L","nsdap_pct":57.77},{"krnr":903,"name":"KRONACH","nsdap_pct":36.09},{"krnr":904,"name":"KULMBACH L","nsdap_pct":61.46},{"krnr":906,"name":"LICHTENFELS","nsdap_pct":40.94},{"krnr":908,"name":"MUENCHBERG","nsdap_pct":55.92},{"krnr":909,"name":"NAILA","nsdap_pct":59.36},{"krnr":911,"name":"PEGNITZ","nsdap_pct":46.39},{"krnr":912,"name":"REHAU","nsdap_pct":58.35},{"krnr":915,"name":"STADTSTEINACH","nsdap_pct":55.89},{"krnr":916,"name":"STAFFELSTEIN","nsdap_pct":45.71},{"krnr":918,"name":"WUNSIEDEL","nsdap_pct":49.62},{"krnr":919,"name":"ANSBACH L","nsdap_pct":75.64},{"krnr":921,"name":"DINKELSBUEHL L","nsdap_pct":71.47},{"krnr":923,"name":"EICHSTAETT L","nsdap_pct":40.51},{"krnr":925,"name":"ERLANGEN L","nsdap_pct":54.13},{"krnr":927,"name":"FEUCHTWANGEN","nsdap_pct":56.59},{"krnr":928,"name":"FUERTH L","nsdap_pct":65.87},{"krnr":930,"name":"GUNZENHAUSEN","nsdap_pct":72.86},{"krnr":931,"name":"HERSBRUCK","nsdap_pct":64.1},{"krnr":932,"name":"HILPOLTSTEIN","nsdap_pct":39.27},{"krnr":933,"name":"LAUF","nsdap_pct":43.48},{"krnr":934,"name":"NEUSTADT (AISCH)","nsdap_pct":79.17},{"krnr":935,"name":"NUERNBERG L","nsdap_pct":63.19},{"krnr":937,"name":"ROTHENBURG (TAUBER) L","nsdap_pct":83.01},{"krnr":939,"name":"SCHEINFELD","nsdap_pct":67.32},{"krnr":940,"name":"SCHWABACH L","nsdap_pct":53.98},{"krnr":942,"name":"UFFENHEIM","nsdap_pct":78.85},{"krnr":943,"name":"WEISSENBURG (BAYERN) L","nsdap_pct":61.25},{"krnr":945,"name":"ALZENAU (UNTERFRANKEN)","nsdap_pct":25.23},{"krnr":946,"name":"ASCHAFFENBURG L","nsdap_pct":19.45},{"krnr":949,"name":"BRUECKENAU","nsdap_pct":47.01},{"krnr":950,"name":"EBERN","nsdap_pct":49.99},{"krnr":951,"name":"GEMUENDEN","nsdap_pct":32.78},{"krnr":952,"name":"GEROLZHOFEN","nsdap_pct":41.2},{"krnr":953,"name":"HAMMELBURG","nsdap_pct":36.21},{"krnr":954,"name":"HASSFURT","nsdap_pct":35.68},{"krnr":955,"name":"HOFHEIM (UNTERFRANKEN)","nsdap_pct":56.66},{"krnr":956,"name":"KARLSTADT","nsdap_pct":29.96},{"krnr":957,"name":"KISSINGEN L","nsdap_pct":29.03},{"krnr":958,"name":"KITZINGEN L","nsdap_pct":56.62},{"krnr":960,"name":"KOENIGSHOFEN (I.GRABFELD)","nsdap_pct":57.39},{"krnr":961,"name":"LOHR","nsdap_pct":22.92},{"krnr":962,"name":"MARKTHEIDENFELD","nsdap_pct":42.75},{"krnr":963,"name":"MELLRICHSTADT","nsdap_pct":39.47},{"krnr":964,"name":"MILTENBERG","nsdap_pct":25.78},{"krnr":965,"name":"NEUSTADT (SAALE)","nsdap_pct":27.61},{"krnr":966,"name":"OBERNBURG","nsdap_pct":22.63},{"krnr":967,"name":"OCHSENFURT","nsdap_pct":33.07},{"krnr":968,"name":"SCHWEINFURT L","nsdap_pct":30.54},{"krnr":970,"name":"WUERZBURG L","nsdap_pct":21.48},{"krnr":972,"name":"BERGZABERN","nsdap_pct":58.9},{"krnr":974,"name":"FRANKENTHAL L","nsdap_pct":42.66},{"krnr":976,"name":"GERMERSHEIM","nsdap_pct":43.49},{"krnr":978,"name":"KAISERSLAUTERN L","nsdap_pct":45.99},{"krnr":980,"name":"KIRCHHEIMBOLANDEN","nsdap_pct":55.7},{"krnr":981,"name":"KUSEL","nsdap_pct":53.64},{"krnr":982,"name":"LANDAU (PFALZ) L","nsdap_pct":53.69},{"krnr":985,"name":"LUDWIGSHAFEN (RHEIN) L","nsdap_pct":42.11},{"krnr":987,"name":"NEUSTADT (HARDT) L","nsdap_pct":52.03},{"krnr":989,"name":"PIRMASENS L","nsdap_pct":41.67},{"krnr":1061,"name":"AALEN","nsdap_pct":29.88},{"krnr":1062,"name":"BACKNANG","nsdap_pct":60.73},{"krnr":1063,"name":"BALINGEN","nsdap_pct":43.1},{"krnr":1064,"name":"BESIGHEIM","nsdap_pct":41.14},{"krnr":1065,"name":"BIBERACH","nsdap_pct":38.86},{"krnr":1066,"name":"BLAUBEUREN","nsdap_pct":46.49},{"krnr":1067,"name":"BOEBLINGEN","nsdap_pct":48.85},{"krnr":1068,"name":"BRACKENHEIM","nsdap_pct":45.26},{"krnr":1069,"name":"CALW","nsdap_pct":61.13},{"krnr":1071,"name":"CRAILSHEIM","nsdap_pct":62.63},{"krnr":1072,"name":"EHINGEN","nsdap_pct":37.91},{"krnr":1073,"name":"ELLWANGEN","nsdap_pct":29.38},{"krnr":1074,"name":"ESSLINGEN","nsdap_pct":35.98},{"krnr":1075,"name":"FREUDENSTADT","nsdap_pct":55.83},{"krnr":1076,"name":"GAILDORF","nsdap_pct":68.2},{"krnr":1077,"name":"GEISLINGEN","nsdap_pct":43.23},{"krnr":1078,"name":"GERABRONN","nsdap_pct":71.8},{"krnr":1079,"name":"GMUEND","nsdap_pct":29.51},{"krnr":1080,"name":"GOEPPINGEN","nsdap_pct":31.33},{"krnr":1081,"name":"HALL","nsdap_pct":57.32},{"krnr":1082,"name":"HEIDENHEIM","nsdap_pct":44.27},{"krnr":1083,"name":"HEILBRONN","nsdap_pct":30.15},{"krnr":1084,"name":"HERRENBERG","nsdap_pct":57.8},{"krnr":1085,"name":"HORB","nsdap_pct":39.95},{"krnr":1086,"name":"KIRCHHEIM","nsdap_pct":57.28},{"krnr":1087,"name":"KUENZELSAU","nsdap_pct":43.35},{"krnr":1088,"name":"LAUPHEIM","nsdap_pct":36.04},{"krnr":1089,"name":"LEONBERG","nsdap_pct":48.28},{"krnr":1090,"name":"LEUTKIRCH","nsdap_pct":39.31},{"krnr":1091,"name":"LUDWIGSBURG","nsdap_pct":39.23},{"krnr":1092,"name":"MARBACH","nsdap_pct":47.41},{"krnr":1093,"name":"MAULBRONN","nsdap_pct":56.4},{"krnr":1094,"name":"MERGENTHEIM","nsdap_pct":50.28},{"krnr":1095,"name":"MUENSINGEN","nsdap_pct":54.16},{"krnr":1096,"name":"NAGOLD","nsdap_pct":66.38},{"krnr":1097,"name":"NECKARSULM","nsdap_pct":36.53},{"krnr":1098,"name":"NERESHEIM","nsdap_pct":32.62},{"krnr":1099,"name":"NEUENBUERG","nsdap_pct":61.01},{"krnr":1100,"name":"NUERTINGEN","nsdap_pct":44.73},{"krnr":1101,"name":"OBERNDORF","nsdap_pct":34.98},{"krnr":1102,"name":"OEHRINGEN","nsdap_pct":63.61},{"krnr":1103,"name":"RAVENSBURG","nsdap_pct":42.18},{"krnr":1104,"name":"REUTLINGEN","nsdap_pct":39.37},{"krnr":1105,"name":"RIEDLINGEN","nsdap_pct":37.53},{"krnr":1106,"name":"ROTTENBURG","nsdap_pct":37.92},{"krnr":1107,"name":"ROTTWEIL","nsdap_pct":31.98},{"krnr":1108,"name":"SAULGAU","nsdap_pct":40.84},{"krnr":1109,"name":"SCHORNDORF","nsdap_pct":47.43},{"krnr":1110,"name":"SPAICHINGEN","nsdap_pct":25.43},{"krnr":1111,"name":"STUTTGART L","nsdap_pct":36.62},{"krnr":1113,"name":"SULZ","nsdap_pct":60.71},{"krnr":1114,"name":"TETTNANG","nsdap_pct":37.61},{"krnr":1115,"name":"TUEBINGEN","nsdap_pct":44.29},{"krnr":1116,"name":"TUTTLINGEN","nsdap_pct":38.38},{"krnr":1117,"name":"ULM","nsdap_pct":47.39},{"krnr":1118,"name":"URACH","nsdap_pct":58.52},{"krnr":1119,"name":"VAIHINGEN (1928- VAHINGEN-ENZ)","nsdap_pct":52.68},{"krnr":1120,"name":"WAIBLINGEN","nsdap_pct":45.38},{"krnr":1121,"name":"WALDSEE","nsdap_pct":37.9},{"krnr":1122,"name":"WANGEN","nsdap_pct":35.92},{"krnr":1124,"name":"WELZHEIM","nsdap_pct":61.48},{"krnr":1125,"name":"HECHINGEN","nsdap_pct":43.91},{"krnr":1126,"name":"SIGMARINGEN","nsdap_pct":35.88},{"krnr":1129,"name":"DONAUESCHINGEN","nsdap_pct":46.07},{"krnr":1130,"name":"ENGEN","nsdap_pct":45.44},{"krnr":1131,"name":"KONSTANZ","nsdap_pct":37.81},{"krnr":1132,"name":"MESSKIRCH","nsdap_pct":43.92},{"krnr":1133,"name":"PFULLENDORF","nsdap_pct":48.21},{"krnr":1134,"name":"SAECKINGEN","nsdap_pct":36.85},{"krnr":1135,"name":"STOCKACH","nsdap_pct":47.61},{"krnr":1136,"name":"UEBERLINGEN","nsdap_pct":49.38},{"krnr":1137,"name":"VILLINGEN","nsdap_pct":42.6},{"krnr":1138,"name":"WALDSHUT","nsdap_pct":44.17},{"krnr":1139,"name":"EMMENDINGEN","nsdap_pct":58.7},{"krnr":1140,"name":"FREIBURG","nsdap_pct":40.47},{"krnr":1141,"name":"KEHL","nsdap_pct":69.05},{"krnr":1142,"name":"LAHR","nsdap_pct":49.11},{"krnr":1143,"name":"LOERRACH","nsdap_pct":45.89},{"krnr":1144,"name":"MUELLHEIM","nsdap_pct":64.41},{"krnr":1145,"name":"NEUSTADT","nsdap_pct":45.7},{"krnr":1146,"name":"OBERKIRCH","nsdap_pct":56.06},{"krnr":1147,"name":"OFFENBURG","nsdap_pct":44.89},{"krnr":1148,"name":"SCHOPFHEIM","nsdap_pct":49.69},{"krnr":1149,"name":"STAUFEN","nsdap_pct":45.63},{"krnr":1150,"name":"WALDKIRCH","nsdap_pct":34.18},{"krnr":1151,"name":"WOLFACH","nsdap_pct":45.21},{"krnr":1152,"name":"BRETTEN","nsdap_pct":60.96},{"krnr":1153,"name":"BRUCHSAL","nsdap_pct":44.51},{"krnr":1154,"name":"BUEHL","nsdap_pct":50.39},{"krnr":1155,"name":"ETTLINGEN","nsdap_pct":30.93},{"krnr":1156,"name":"KARLSRUHE","nsdap_pct":46.44},{"krnr":991,"name":"ROCKENHAUSEN","nsdap_pct":63.45},{"krnr":992,"name":"SPEYER L","nsdap_pct":29.28},{"krnr":994,"name":"ZWEIBRUECKEN L","nsdap_pct":55.63},{"krnr":997,"name":"DIPPOLDISWALDE","nsdap_pct":55.37},{"krnr":998,"name":"DRESDEN L","nsdap_pct":39.15},{"krnr":1002,"name":"FREIBERG L","nsdap_pct":57.07},{"krnr":1006,"name":"GROSSENHAIN","nsdap_pct":48.59},{"krnr":1007,"name":"MEISSEN L","nsdap_pct":46.97},{"krnr":1010,"name":"PIRNA L","nsdap_pct":41.4},{"krnr":1016,"name":"BAUTZEN L","nsdap_pct":48.72},{"krnr":1018,"name":"KAMENZ","nsdap_pct":47.5},{"krnr":1019,"name":"LOEBAU","nsdap_pct":45.9},{"krnr":1020,"name":"ZITTAU L","nsdap_pct":39.58},{"krnr":1024,"name":"BORNA","nsdap_pct":44.39},{"krnr":1025,"name":"DOEBELN L","nsdap_pct":47.13},{"krnr":1028,"name":"GRIMMA","nsdap_pct":46.72},{"krnr":1029,"name":"LEIPZIG L","nsdap_pct":33.21},{"krnr":1032,"name":"OSCHATZ","nsdap_pct":46.07},{"krnr":1034,"name":"ROCHLITZ","nsdap_pct":48.27},{"krnr":1039,"name":"ANNABERG","nsdap_pct":55.86},{"krnr":1040,"name":"CHEMNITZ L","nsdap_pct":42.53},{"krnr":1042,"name":"FLOEHA","nsdap_pct":50.03},{"krnr":1044,"name":"GLAUCHAU L","nsdap_pct":48.17},{"krnr":1046,"name":"MARIENBERG","nsdap_pct":57.14},{"krnr":1048,"name":"STOLLBERG","nsdap_pct":46.21},{"krnr":1050,"name":"AUERBACH","nsdap_pct":61.65},{"krnr":1052,"name":"OELSNITZ","nsdap_pct":62.91},{"krnr":1053,"name":"PLAUEN L","nsdap_pct":60.66},{"krnr":1056,"name":"SCHWARZENBERG","nsdap_pct":51.94},{"krnr":1059,"name":"ZWICKAU L","nsdap_pct":46.48},{"krnr":1157,"name":"PFORZHEIM","nsdap_pct":57.51},{"krnr":1158,"name":"RASTATT","nsdap_pct":39.83},{"krnr":1159,"name":"ADELSHEIM","nsdap_pct":55.58},{"krnr":1160,"name":"BUCHEN","nsdap_pct":38.23},{"krnr":1161,"name":"HEIDELBERG","nsdap_pct":46.05},{"krnr":1162,"name":"MANNHEIM","nsdap_pct":36.41},{"krnr":1163,"name":"MOSBACH","nsdap_pct":52.68},{"krnr":1164,"name":"SINSHEIM","nsdap_pct":64.06},{"krnr":1165,"name":"TAUBERBISCHOFSHEIM","nsdap_pct":41.23},{"krnr":1166,"name":"WEINHEIM","nsdap_pct":44.2},{"krnr":1167,"name":"WERTHEIM","nsdap_pct":60.78},{"krnr":1168,"name":"WIESLOCH","nsdap_pct":35.89},{"krnr":1169,"name":"BENSHEIM","nsdap_pct":44.61},{"krnr":1170,"name":"DARMSTADT","nsdap_pct":48.12},{"krnr":1171,"name":"DIEBURG","nsdap_pct":49.32},{"krnr":1172,"name":"ERBACH","nsdap_pct":64.41},{"krnr":1173,"name":"GROSS GERAU","nsdap_pct":41.99},{"krnr":1174,"name":"HEPPENHEIM","nsdap_pct":34.84},{"krnr":1175,"name":"OFFENBACH","nsdap_pct":30.4},{"krnr":1176,"name":"ALSFELD","nsdap_pct":77.83},{"krnr":1177,"name":"BUEDINGEN","nsdap_pct":71.02},{"krnr":1178,"name":"FRIEDBERG","nsdap_pct":48.77},{"krnr":1179,"name":"GIESSEN","nsdap_pct":58.09},{"krnr":1180,"name":"LAUTERBACH","nsdap_pct":78.61},{"krnr":1181,"name":"SCHOTTEN","nsdap_pct":82.88},{"krnr":1182,"name":"ALZEY","nsdap_pct":55.37},{"krnr":1183,"name":"BINGEN","nsdap_pct":37.93},{"krnr":1184,"name":"MAINZ","nsdap_pct":36.25},{"krnr":1185,"name":"OPPENHEIM","nsdap_pct":55.48},{"krnr":1186,"name":"WORMS","nsdap_pct":46.1},{"krnr":1192,"name":"GEESTLANDE (-30.4.28)","nsdap_pct":38.4},{"krnr":1193,"name":"MARSCHLANDE (-30.4.28)","nsdap_pct":50.4},{"krnr":1195,"name":"RITZEBUETTEL OHNE CUXHAVEN","nsdap_pct":35.33},{"krnr":1196,"name":"VIERLANDE","nsdap_pct":60.88},{"krnr":1207,"name":"GREVESMUEHLEN (-14.1.34)","nsdap_pct":52.65},{"krnr":1209,"name":"GUESTROW L","nsdap_pct":48.96},{"krnr":1211,"name":"HAGENOW","nsdap_pct":55.64},{"krnr":1212,"name":"LUDWIGSLUST","nsdap_pct":53.93},{"krnr":1213,"name":"MALCHIN","nsdap_pct":52.76},{"krnr":1214,"name":"PARCHIM","nsdap_pct":55.04},{"krnr":1217,"name":"ROSTOCK L","nsdap_pct":50.96},{"krnr":1220,"name":"SCHWERIN L","nsdap_pct":56.71},{"krnr":1222,"name":"WAREN","nsdap_pct":52.24},{"krnr":1225,"name":"WISMAR L","nsdap_pct":48.74},{"krnr":1236,"name":"SCHOENBERG L","nsdap_pct":52.7},{"krnr":1238,"name":"STARGARD L","nsdap_pct":61.03},{"krnr":1241,"name":"STRELITZ L (-14.1.34)","nsdap_pct":53.68},{"krnr":1245,"name":"LUEBECK L","nsdap_pct":54.18}]